CHANGES.rst
MANIFEST.in
README.rst
setup.py
pyramid_upwork/__init__.py
pyramid_upwork/models.py
pyramid_upwork/tests.py
pyramid_upwork/utils.py
pyramid_upwork/views.py
pyramid_upwork.egg-info/PKG-INFO
pyramid_upwork.egg-info/SOURCES.txt
pyramid_upwork.egg-info/dependency_links.txt
pyramid_upwork.egg-info/not-zip-safe
pyramid_upwork.egg-info/requires.txt
pyramid_upwork.egg-info/top_level.txt
pyramid_upwork/templates/forbidden.jinja2