Metadata-Version: 1.1
Name: pyramid-upwork
Version: 1.1.6
Summary: pyramid_upwork
Home-page: https://github.com/kipanshi/pyramid_upwork
Author: Cyril Panshine
Author-email: kipanshi@gmail.com
License: UNKNOWN
Keywords: web pyramid pylons authentication upwork oauth
Platform: UNKNOWN
Classifier: Programming Language :: Python
Classifier: Programming Language :: Python :: 2
Classifier: Framework :: Pyramid
Classifier: Topic :: Internet :: WWW/HTTP
